__init__.py
config.py
logger.py
utils.py
data/__init__.py
data/data_manager.py
features/__init__.py
models/__init__.py
models/svm/__init__.py
models/svm/train.py
preprocessing/base.py
preprocessing/poc_preprocessor.py
preprocessing/registery.py
visualization/__init__.py
visualization/visualize.py
faps_hassan_rady-1.0.0.dist-info/LICENSE
faps_hassan_rady-1.0.0.dist-info/METADATA
faps_hassan_rady-1.0.0.dist-info/WHEEL
faps_hassan_rady-1.0.0.dist-info/top_level.txt
faps_hassan_rady-1.0.0.dist-info/RECORD
